pool_resources/__init__.py
pool_resources/logger.py
pool_resources/pool_resources.py
pool_resources/resource/__init__.py
pool_resources/resource/resource.py
pool_resources/resource/torch_resource.py
pool_resources-0.1.dist-info/METADATA
pool_resources-0.1.dist-info/WHEEL
pool_resources-0.1.dist-info/top_level.txt
pool_resources-0.1.dist-info/RECORD
