Metadata-Version: 2.1
Name: pool-resources
Version: 0.1
Summary: Pool Resources
Home-page: https://gitlab.com/mihaicristianpirvu/pool-resources
License: WTFPL
Requires-Python: >=3.8
Requires-Dist: torch (>=1.13.1)
Requires-Dist: pytorch-lightning (>=1.6)
